{
  "op": "-",
  "seed": 2,
  "p": 401,
  "correct_basis": "additive",
  "base_test_acc": 1.0,
  "readout_eff_rank": 10.429,
  "k_eff_embedding": 7.561,
  "k_active_embedding": 10,
  "k_readout_participation": 5.7,
  "n_active": 10,
  "n_used_freqs": 8,
  "n_unused_freqs": 2,
  "unused_fraction": 0.2,
  "k_readout_over_k_eff": 0.754,
  "two_k_readout_over_readout_rank": 1.093,
  "active_freqs": [
    22,
    29,
    52,
    85,
    111,
    112,
    153,
    165,
    176,
    186
  ],
  "importance_per_freq": {
    "22": 0.1089,
    "29": 0.0448,
    "52": 0.0145,
    "85": 0.7226,
    "111": 0.5101,
    "112": 0.4751,
    "153": 0.6609,
    "165": 0.6345,
    "176": 0.6982,
    "186": 0.1309
  },
  "acc_after_ablate_per_freq": {
    "22": 1.0,
    "29": 1.0,
    "52": 1.0,
    "85": 0.472,
    "111": 0.792,
    "112": 0.7685,
    "153": 0.56,
    "165": 0.5415,
    "176": 0.4725,
    "186": 1.0
  },
  "rescue_hypothesis": "2*k_readout ~= readout_eff_rank (the law counts the irreps the readout USES, not those the embedding allocates)"
}