{
  "mode": "thermo_specific_heat",
  "date": "2026-06-29",
  "models": [
    "pythia-410m",
    "pythia-1.4b",
    "gpt2-medium"
  ],
  "tasks": [
    "induction",
    "relation_composition"
  ],
  "n_samples": 32,
  "seed": 0,
  "peak_spread_max": 0.2,
  "null_margin": 2.0,
  "cells": [
    {
      "model": "pythia-410m",
      "hf_name": "EleutherAI/pythia-410m",
      "domain": "induction",
      "n_samples": 32,
      "n_layers": 24,
      "rel_depth": [
        0.0,
        0.0435,
        0.087,
        0.1304,
        0.1739,
        0.2174,
        0.2609,
        0.3043,
        0.3478,
        0.3913,
        0.4348,
        0.4783,
        0.5217,
        0.5652,
        0.6087,
        0.6522,
        0.6957,
        0.7391,
        0.7826,
        0.8261,
        0.8696,
        0.913,
        0.9565,
        1.0
      ],
      "entropy_H": [
        2.0605,
        1.7133,
        2.1408,
        2.1117,
        2.2011,
        1.8484,
        1.2296,
        1.2283,
        1.5403,
        1.3099,
        1.3372,
        1.1262,
        1.4752,
        0.9822,
        0.8583,
        0.9745,
        0.9745,
        0.9734,
        0.8404,
        0.9218,
        0.6395,
        0.8975,
        0.7743,
        0.5043
      ],
      "specific_heat_C": [
        0.830631,
        0.991754,
        0.736557,
        0.765029,
        0.669787,
        0.871526,
        1.44741,
        1.307894,
        1.115743,
        1.339288,
        1.305372,
        1.494562,
        1.528652,
        1.78691,
        1.502569,
        1.593303,
        1.56393,
        1.45354,
        1.274421,
        1.211229,
        0.670333,
        0.952783,
        0.720422,
        0.593771
      ],
      "null_C": [
        0.830631,
        0.991754,
        0.736557,
        0.765029,
        0.669787,
        0.871526,
        1.44741,
        1.307894,
        1.115743,
        1.339288,
        1.305372,
        1.494562,
        1.528652,
        1.78691,
        1.502569,
        1.593303,
        1.56393,
        1.45354,
        1.274421,
        1.211229,
        0.670333,
        0.952783,
        0.720422,
        0.593771
      ],
      "null_level_mean": 1.155309,
      "peak": {
        "peak_layer": 13,
        "peak_rel_depth": 0.5652,
        "peak_C": 1.78691
      },
      "peak_rel_depth_per_prompt": [
        0.4783,
        0.5652,
        0.5652,
        0.6522,
        0.5652,
        0.6957,
        0.5652,
        0.5652,
        0.5652,
        0.5652,
        0.5652,
        0.5652,
        0.6522,
        0.5652,
        0.6957,
        0.5652,
        0.5652,
        0.5652,
        0.5652,
        0.5652,
        0.5652,
        0.5652,
        0.5652,
        0.5652,
        0.5652,
        0.5217,
        0.5652,
        0.5652,
        0.5217,
        0.5652,
        0.5652,
        0.5652
      ],
      "peak_rel_depth_spread": 0.2174,
      "peak_over_null": 1.5467,
      "verdict": "smooth",
      "wall_s": 13.4
    },
    {
      "model": "pythia-410m",
      "hf_name": "EleutherAI/pythia-410m",
      "domain": "relation_composition",
      "n_samples": 32,
      "n_layers": 24,
      "rel_depth": [
        0.0,
        0.0435,
        0.087,
        0.1304,
        0.1739,
        0.2174,
        0.2609,
        0.3043,
        0.3478,
        0.3913,
        0.4348,
        0.4783,
        0.5217,
        0.5652,
        0.6087,
        0.6522,
        0.6957,
        0.7391,
        0.7826,
        0.8261,
        0.8696,
        0.913,
        0.9565,
        1.0
      ],
      "entropy_H": [
        2.1369,
        1.8074,
        2.2138,
        2.1312,
        2.2026,
        1.8829,
        1.2861,
        1.242,
        1.5268,
        1.4503,
        1.3584,
        1.2826,
        1.4445,
        1.1501,
        0.9327,
        1.0823,
        1.2366,
        1.1608,
        1.2246,
        1.2383,
        0.834,
        1.0949,
        0.9534,
        0.7079
      ],
      "specific_heat_C": [
        0.907093,
        1.079972,
        0.909322,
        0.882156,
        0.817906,
        0.920426,
        1.560812,
        1.421078,
        1.309882,
        1.479884,
        1.494573,
        1.711261,
        1.724688,
        1.864113,
        1.682014,
        1.746258,
        1.778231,
        1.641663,
        1.370744,
        1.37246,
        0.826589,
        1.062409,
        0.903799,
        0.864279
      ],
      "null_C": [
        0.907093,
        1.079972,
        0.909322,
        0.882156,
        0.817906,
        0.920426,
        1.560812,
        1.421078,
        1.309882,
        1.479884,
        1.494573,
        1.711261,
        1.724688,
        1.864113,
        1.682014,
        1.746258,
        1.778231,
        1.641663,
        1.370744,
        1.37246,
        0.826589,
        1.062409,
        0.903799,
        0.864279
      ],
      "null_level_mean": 1.305484,
      "peak": {
        "peak_layer": 13,
        "peak_rel_depth": 0.5652,
        "peak_C": 1.864113
      },
      "peak_rel_depth_per_prompt": [
        0.5652,
        0.5652,
        0.7391,
        0.6957,
        0.5217,
        0.5652,
        0.5217,
        0.5652,
        0.6957,
        0.6957,
        0.5652,
        0.6957,
        0.6957,
        0.5652,
        0.5652,
        0.6957,
        0.4783,
        0.6957,
        0.5652,
        0.5652,
        0.6957,
        0.6957,
        0.5652,
        0.5652,
        0.7391,
        0.5652,
        0.5652,
        0.5652,
        0.5652,
        0.6957,
        0.5652,
        0.5652
      ],
      "peak_rel_depth_spread": 0.2608,
      "peak_over_null": 1.4279,
      "verdict": "smooth",
      "wall_s": 7.1
    },
    {
      "model": "pythia-1.4b",
      "hf_name": "EleutherAI/pythia-1.4b",
      "domain": "induction",
      "n_samples": 32,
      "n_layers": 24,
      "rel_depth": [
        0.0,
        0.0435,
        0.087,
        0.1304,
        0.1739,
        0.2174,
        0.2609,
        0.3043,
        0.3478,
        0.3913,
        0.4348,
        0.4783,
        0.5217,
        0.5652,
        0.6087,
        0.6522,
        0.6957,
        0.7391,
        0.7826,
        0.8261,
        0.8696,
        0.913,
        0.9565,
        1.0
      ],
      "entropy_H": [
        2.0492,
        1.8186,
        1.9837,
        2.069,
        1.1972,
        1.1896,
        1.4482,
        1.4575,
        1.6337,
        1.4707,
        1.3188,
        1.3687,
        1.2507,
        1.0775,
        1.0006,
        1.0918,
        0.8721,
        0.8293,
        0.982,
        1.0767,
        1.181,
        1.0435,
        0.9316,
        0.9199
      ],
      "specific_heat_C": [
        0.833478,
        0.940661,
        0.805457,
        0.800803,
        1.44573,
        1.260913,
        1.388027,
        1.262348,
        1.243355,
        1.579496,
        1.46552,
        1.530927,
        1.383247,
        1.43034,
        1.49765,
        1.367106,
        1.17646,
        1.193512,
        1.210203,
        1.222444,
        1.215078,
        1.13424,
        1.120631,
        0.959019
      ],
      "null_C": [
        0.833478,
        0.940661,
        0.805457,
        0.800803,
        1.44573,
        1.260913,
        1.388027,
        1.262348,
        1.243355,
        1.579496,
        1.46552,
        1.530927,
        1.383247,
        1.43034,
        1.49765,
        1.367106,
        1.17646,
        1.193512,
        1.210203,
        1.222444,
        1.215078,
        1.13424,
        1.120631,
        0.959019
      ],
      "null_level_mean": 1.227777,
      "peak": {
        "peak_layer": 9,
        "peak_rel_depth": 0.3913,
        "peak_C": 1.579496
      },
      "peak_rel_depth_per_prompt": [
        0.3913,
        0.6087,
        0.1739,
        0.3913,
        0.3913,
        0.3913,
        0.3913,
        0.3913,
        0.3913,
        0.4783,
        0.2609,
        0.3913,
        0.6087,
        0.5652,
        0.1739,
        0.3913,
        0.3913,
        0.4783,
        0.4348,
        0.3913,
        0.6087,
        0.3913,
        0.3913,
        0.3913,
        0.6087,
        0.1739,
        0.4783,
        0.6087,
        0.3913,
        0.6087,
        0.6522,
        0.4783
      ],
      "peak_rel_depth_spread": 0.4783,
      "peak_over_null": 1.2865,
      "verdict": "smooth",
      "wall_s": 3631.5
    },
    {
      "model": "pythia-1.4b",
      "hf_name": "EleutherAI/pythia-1.4b",
      "domain": "relation_composition",
      "n_samples": 32,
      "n_layers": 24,
      "rel_depth": [
        0.0,
        0.0435,
        0.087,
        0.1304,
        0.1739,
        0.2174,
        0.2609,
        0.3043,
        0.3478,
        0.3913,
        0.4348,
        0.4783,
        0.5217,
        0.5652,
        0.6087,
        0.6522,
        0.6957,
        0.7391,
        0.7826,
        0.8261,
        0.8696,
        0.913,
        0.9565,
        1.0
      ],
      "entropy_H": [
        2.1257,
        1.8257,
        2.0848,
        2.0712,
        1.2807,
        1.2504,
        1.4384,
        1.453,
        1.6636,
        1.453,
        1.3913,
        1.5009,
        1.2622,
        1.2055,
        1.1118,
        1.2191,
        1.0586,
        0.9444,
        1.0628,
        1.1421,
        1.2247,
        1.1355,
        0.9036,
        1.0117
      ],
      "specific_heat_C": [
        0.920486,
        1.053056,
        0.939914,
        0.922342,
        1.537833,
        1.3604,
        1.470549,
        1.443591,
        1.336168,
        1.774762,
        1.535311,
        1.586829,
        1.559769,
        1.462834,
        1.638296,
        1.446253,
        1.235756,
        1.311619,
        1.392483,
        1.353855,
        1.298594,
        1.250238,
        1.186144,
        1.024902
      ],
      "null_C": [
        0.920486,
        1.053056,
        0.939914,
        0.922342,
        1.537833,
        1.3604,
        1.470549,
        1.443591,
        1.336168,
        1.774762,
        1.535311,
        1.586829,
        1.559769,
        1.462834,
        1.638296,
        1.446253,
        1.235756,
        1.311619,
        1.392483,
        1.353855,
        1.298594,
        1.250238,
        1.186144,
        1.024902
      ],
      "null_level_mean": 1.335083,
      "peak": {
        "peak_layer": 9,
        "peak_rel_depth": 0.3913,
        "peak_C": 1.774762
      },
      "peak_rel_depth_per_prompt": [
        0.3913,
        0.3913,
        0.3913,
        0.3913,
        0.3913,
        0.3913,
        0.3913,
        0.6087,
        0.6087,
        0.3913,
        0.3913,
        0.3913,
        0.3913,
        0.3913,
        0.3913,
        0.3913,
        0.3913,
        0.4348,
        0.1739,
        0.3913,
        0.3913,
        0.6087,
        0.3913,
        0.3913,
        0.1739,
        0.3913,
        0.2609,
        0.6957,
        0.4783,
        0.3913,
        0.3913,
        0.4783
      ],
      "peak_rel_depth_spread": 0.5218,
      "peak_over_null": 1.3293,
      "verdict": "smooth",
      "wall_s": 499.3
    },
    {
      "model": "gpt2-medium",
      "hf_name": "gpt2-medium",
      "domain": "induction",
      "n_samples": 32,
      "n_layers": 24,
      "rel_depth": [
        0.0,
        0.0435,
        0.087,
        0.1304,
        0.1739,
        0.2174,
        0.2609,
        0.3043,
        0.3478,
        0.3913,
        0.4348,
        0.4783,
        0.5217,
        0.5652,
        0.6087,
        0.6522,
        0.6957,
        0.7391,
        0.7826,
        0.8261,
        0.8696,
        0.913,
        0.9565,
        1.0
      ],
      "entropy_H": [
        2.5371,
        2.2297,
        2.2087,
        1.8632,
        1.4665,
        1.2028,
        1.1449,
        1.3096,
        1.4886,
        1.2801,
        1.6178,
        1.4108,
        1.133,
        0.9644,
        1.0489,
        1.1563,
        0.9308,
        1.0511,
        1.1275,
        1.1929,
        1.2186,
        1.2476,
        1.6151,
        1.8177
      ],
      "specific_heat_C": [
        0.333946,
        0.808691,
        0.792365,
        1.018927,
        1.310177,
        1.356701,
        1.408536,
        1.305389,
        1.471779,
        1.397727,
        1.333621,
        1.455003,
        1.524536,
        1.529527,
        1.561514,
        1.642178,
        1.654562,
        1.605069,
        1.506153,
        1.611686,
        1.51,
        1.475312,
        1.385524,
        1.170695
      ],
      "null_C": [
        0.333946,
        0.808691,
        0.792365,
        1.018927,
        1.310177,
        1.356701,
        1.408536,
        1.305389,
        1.471779,
        1.397727,
        1.333621,
        1.455003,
        1.524536,
        1.529527,
        1.561514,
        1.642178,
        1.654562,
        1.605069,
        1.506153,
        1.611686,
        1.51,
        1.475312,
        1.385524,
        1.170695
      ],
      "null_level_mean": 1.340401,
      "peak": {
        "peak_layer": 16,
        "peak_rel_depth": 0.6957,
        "peak_C": 1.654562
      },
      "peak_rel_depth_per_prompt": [
        0.6522,
        0.9565,
        0.6522,
        0.8261,
        0.8261,
        0.6087,
        0.5652,
        0.6957,
        0.8261,
        0.6522,
        0.7391,
        0.6957,
        0.913,
        0.9565,
        0.6522,
        0.6957,
        0.7391,
        0.6522,
        0.6087,
        0.6522,
        0.8261,
        0.6522,
        0.6957,
        0.6522,
        0.8261,
        0.6522,
        0.8261,
        0.9565,
        0.4348,
        0.6957,
        0.6957,
        0.8261
      ],
      "peak_rel_depth_spread": 0.5217,
      "peak_over_null": 1.2344,
      "verdict": "smooth",
      "wall_s": 8.4
    },
    {
      "model": "gpt2-medium",
      "hf_name": "gpt2-medium",
      "domain": "relation_composition",
      "n_samples": 32,
      "n_layers": 24,
      "rel_depth": [
        0.0,
        0.0435,
        0.087,
        0.1304,
        0.1739,
        0.2174,
        0.2609,
        0.3043,
        0.3478,
        0.3913,
        0.4348,
        0.4783,
        0.5217,
        0.5652,
        0.6087,
        0.6522,
        0.6957,
        0.7391,
        0.7826,
        0.8261,
        0.8696,
        0.913,
        0.9565,
        1.0
      ],
      "entropy_H": [
        2.6544,
        2.3477,
        2.29,
        1.9226,
        1.5266,
        1.2598,
        1.1865,
        1.3609,
        1.5661,
        1.2886,
        1.5933,
        1.4493,
        1.3646,
        1.0951,
        1.2554,
        1.3332,
        0.9801,
        1.1841,
        1.4122,
        1.4917,
        1.5954,
        1.5333,
        1.8607,
        2.0741
      ],
      "specific_heat_C": [
        0.347517,
        0.825803,
        0.865112,
        1.041266,
        1.358549,
        1.381077,
        1.466934,
        1.445545,
        1.565073,
        1.541317,
        1.494068,
        1.633081,
        1.640579,
        1.945909,
        1.769004,
        1.766905,
        1.743659,
        1.761892,
        1.6446,
        1.67395,
        1.545649,
        1.460886,
        1.356562,
        1.143656
      ],
      "null_C": [
        0.347517,
        0.825803,
        0.865112,
        1.041266,
        1.358549,
        1.381077,
        1.466934,
        1.445545,
        1.565073,
        1.541317,
        1.494068,
        1.633081,
        1.640579,
        1.945909,
        1.769004,
        1.766905,
        1.743659,
        1.761892,
        1.6446,
        1.67395,
        1.545649,
        1.460886,
        1.356562,
        1.143656
      ],
      "null_level_mean": 1.434108,
      "peak": {
        "peak_layer": 13,
        "peak_rel_depth": 0.5652,
        "peak_C": 1.945909
      },
      "peak_rel_depth_per_prompt": [
        0.8261,
        0.5652,
        0.5652,
        0.6087,
        0.5652,
        0.5652,
        0.7391,
        0.5652,
        0.5652,
        0.5652,
        0.5652,
        0.7391,
        0.6957,
        0.5652,
        0.5652,
        0.5217,
        0.6957,
        0.6957,
        0.6087,
        0.5652,
        0.5652,
        0.5652,
        0.8261,
        0.5652,
        0.5652,
        0.5652,
        0.5652,
        0.5652,
        0.5652,
        0.6957,
        0.5652,
        0.5652
      ],
      "peak_rel_depth_spread": 0.3044,
      "peak_over_null": 1.3569,
      "verdict": "smooth",
      "wall_s": 11.2
    }
  ],
  "per_model": {
    "pythia-410m": {
      "induction": {
        "model": "pythia-410m",
        "hf_name": "EleutherAI/pythia-410m",
        "domain": "induction",
        "n_samples": 32,
        "n_layers": 24,
        "rel_depth": [
          0.0,
          0.0435,
          0.087,
          0.1304,
          0.1739,
          0.2174,
          0.2609,
          0.3043,
          0.3478,
          0.3913,
          0.4348,
          0.4783,
          0.5217,
          0.5652,
          0.6087,
          0.6522,
          0.6957,
          0.7391,
          0.7826,
          0.8261,
          0.8696,
          0.913,
          0.9565,
          1.0
        ],
        "entropy_H": [
          2.0605,
          1.7133,
          2.1408,
          2.1117,
          2.2011,
          1.8484,
          1.2296,
          1.2283,
          1.5403,
          1.3099,
          1.3372,
          1.1262,
          1.4752,
          0.9822,
          0.8583,
          0.9745,
          0.9745,
          0.9734,
          0.8404,
          0.9218,
          0.6395,
          0.8975,
          0.7743,
          0.5043
        ],
        "specific_heat_C": [
          0.830631,
          0.991754,
          0.736557,
          0.765029,
          0.669787,
          0.871526,
          1.44741,
          1.307894,
          1.115743,
          1.339288,
          1.305372,
          1.494562,
          1.528652,
          1.78691,
          1.502569,
          1.593303,
          1.56393,
          1.45354,
          1.274421,
          1.211229,
          0.670333,
          0.952783,
          0.720422,
          0.593771
        ],
        "null_C": [
          0.830631,
          0.991754,
          0.736557,
          0.765029,
          0.669787,
          0.871526,
          1.44741,
          1.307894,
          1.115743,
          1.339288,
          1.305372,
          1.494562,
          1.528652,
          1.78691,
          1.502569,
          1.593303,
          1.56393,
          1.45354,
          1.274421,
          1.211229,
          0.670333,
          0.952783,
          0.720422,
          0.593771
        ],
        "null_level_mean": 1.155309,
        "peak": {
          "peak_layer": 13,
          "peak_rel_depth": 0.5652,
          "peak_C": 1.78691
        },
        "peak_rel_depth_per_prompt": [
          0.4783,
          0.5652,
          0.5652,
          0.6522,
          0.5652,
          0.6957,
          0.5652,
          0.5652,
          0.5652,
          0.5652,
          0.5652,
          0.5652,
          0.6522,
          0.5652,
          0.6957,
          0.5652,
          0.5652,
          0.5652,
          0.5652,
          0.5652,
          0.5652,
          0.5652,
          0.5652,
          0.5652,
          0.5652,
          0.5217,
          0.5652,
          0.5652,
          0.5217,
          0.5652,
          0.5652,
          0.5652
        ],
        "peak_rel_depth_spread": 0.2174,
        "peak_over_null": 1.5467,
        "verdict": "smooth",
        "wall_s": 13.4
      },
      "relation_composition": {
        "model": "pythia-410m",
        "hf_name": "EleutherAI/pythia-410m",
        "domain": "relation_composition",
        "n_samples": 32,
        "n_layers": 24,
        "rel_depth": [
          0.0,
          0.0435,
          0.087,
          0.1304,
          0.1739,
          0.2174,
          0.2609,
          0.3043,
          0.3478,
          0.3913,
          0.4348,
          0.4783,
          0.5217,
          0.5652,
          0.6087,
          0.6522,
          0.6957,
          0.7391,
          0.7826,
          0.8261,
          0.8696,
          0.913,
          0.9565,
          1.0
        ],
        "entropy_H": [
          2.1369,
          1.8074,
          2.2138,
          2.1312,
          2.2026,
          1.8829,
          1.2861,
          1.242,
          1.5268,
          1.4503,
          1.3584,
          1.2826,
          1.4445,
          1.1501,
          0.9327,
          1.0823,
          1.2366,
          1.1608,
          1.2246,
          1.2383,
          0.834,
          1.0949,
          0.9534,
          0.7079
        ],
        "specific_heat_C": [
          0.907093,
          1.079972,
          0.909322,
          0.882156,
          0.817906,
          0.920426,
          1.560812,
          1.421078,
          1.309882,
          1.479884,
          1.494573,
          1.711261,
          1.724688,
          1.864113,
          1.682014,
          1.746258,
          1.778231,
          1.641663,
          1.370744,
          1.37246,
          0.826589,
          1.062409,
          0.903799,
          0.864279
        ],
        "null_C": [
          0.907093,
          1.079972,
          0.909322,
          0.882156,
          0.817906,
          0.920426,
          1.560812,
          1.421078,
          1.309882,
          1.479884,
          1.494573,
          1.711261,
          1.724688,
          1.864113,
          1.682014,
          1.746258,
          1.778231,
          1.641663,
          1.370744,
          1.37246,
          0.826589,
          1.062409,
          0.903799,
          0.864279
        ],
        "null_level_mean": 1.305484,
        "peak": {
          "peak_layer": 13,
          "peak_rel_depth": 0.5652,
          "peak_C": 1.864113
        },
        "peak_rel_depth_per_prompt": [
          0.5652,
          0.5652,
          0.7391,
          0.6957,
          0.5217,
          0.5652,
          0.5217,
          0.5652,
          0.6957,
          0.6957,
          0.5652,
          0.6957,
          0.6957,
          0.5652,
          0.5652,
          0.6957,
          0.4783,
          0.6957,
          0.5652,
          0.5652,
          0.6957,
          0.6957,
          0.5652,
          0.5652,
          0.7391,
          0.5652,
          0.5652,
          0.5652,
          0.5652,
          0.6957,
          0.5652,
          0.5652
        ],
        "peak_rel_depth_spread": 0.2608,
        "peak_over_null": 1.4279,
        "verdict": "smooth",
        "wall_s": 7.1
      }
    },
    "pythia-1.4b": {
      "induction": {
        "model": "pythia-1.4b",
        "hf_name": "EleutherAI/pythia-1.4b",
        "domain": "induction",
        "n_samples": 32,
        "n_layers": 24,
        "rel_depth": [
          0.0,
          0.0435,
          0.087,
          0.1304,
          0.1739,
          0.2174,
          0.2609,
          0.3043,
          0.3478,
          0.3913,
          0.4348,
          0.4783,
          0.5217,
          0.5652,
          0.6087,
          0.6522,
          0.6957,
          0.7391,
          0.7826,
          0.8261,
          0.8696,
          0.913,
          0.9565,
          1.0
        ],
        "entropy_H": [
          2.0492,
          1.8186,
          1.9837,
          2.069,
          1.1972,
          1.1896,
          1.4482,
          1.4575,
          1.6337,
          1.4707,
          1.3188,
          1.3687,
          1.2507,
          1.0775,
          1.0006,
          1.0918,
          0.8721,
          0.8293,
          0.982,
          1.0767,
          1.181,
          1.0435,
          0.9316,
          0.9199
        ],
        "specific_heat_C": [
          0.833478,
          0.940661,
          0.805457,
          0.800803,
          1.44573,
          1.260913,
          1.388027,
          1.262348,
          1.243355,
          1.579496,
          1.46552,
          1.530927,
          1.383247,
          1.43034,
          1.49765,
          1.367106,
          1.17646,
          1.193512,
          1.210203,
          1.222444,
          1.215078,
          1.13424,
          1.120631,
          0.959019
        ],
        "null_C": [
          0.833478,
          0.940661,
          0.805457,
          0.800803,
          1.44573,
          1.260913,
          1.388027,
          1.262348,
          1.243355,
          1.579496,
          1.46552,
          1.530927,
          1.383247,
          1.43034,
          1.49765,
          1.367106,
          1.17646,
          1.193512,
          1.210203,
          1.222444,
          1.215078,
          1.13424,
          1.120631,
          0.959019
        ],
        "null_level_mean": 1.227777,
        "peak": {
          "peak_layer": 9,
          "peak_rel_depth": 0.3913,
          "peak_C": 1.579496
        },
        "peak_rel_depth_per_prompt": [
          0.3913,
          0.6087,
          0.1739,
          0.3913,
          0.3913,
          0.3913,
          0.3913,
          0.3913,
          0.3913,
          0.4783,
          0.2609,
          0.3913,
          0.6087,
          0.5652,
          0.1739,
          0.3913,
          0.3913,
          0.4783,
          0.4348,
          0.3913,
          0.6087,
          0.3913,
          0.3913,
          0.3913,
          0.6087,
          0.1739,
          0.4783,
          0.6087,
          0.3913,
          0.6087,
          0.6522,
          0.4783
        ],
        "peak_rel_depth_spread": 0.4783,
        "peak_over_null": 1.2865,
        "verdict": "smooth",
        "wall_s": 3631.5
      },
      "relation_composition": {
        "model": "pythia-1.4b",
        "hf_name": "EleutherAI/pythia-1.4b",
        "domain": "relation_composition",
        "n_samples": 32,
        "n_layers": 24,
        "rel_depth": [
          0.0,
          0.0435,
          0.087,
          0.1304,
          0.1739,
          0.2174,
          0.2609,
          0.3043,
          0.3478,
          0.3913,
          0.4348,
          0.4783,
          0.5217,
          0.5652,
          0.6087,
          0.6522,
          0.6957,
          0.7391,
          0.7826,
          0.8261,
          0.8696,
          0.913,
          0.9565,
          1.0
        ],
        "entropy_H": [
          2.1257,
          1.8257,
          2.0848,
          2.0712,
          1.2807,
          1.2504,
          1.4384,
          1.453,
          1.6636,
          1.453,
          1.3913,
          1.5009,
          1.2622,
          1.2055,
          1.1118,
          1.2191,
          1.0586,
          0.9444,
          1.0628,
          1.1421,
          1.2247,
          1.1355,
          0.9036,
          1.0117
        ],
        "specific_heat_C": [
          0.920486,
          1.053056,
          0.939914,
          0.922342,
          1.537833,
          1.3604,
          1.470549,
          1.443591,
          1.336168,
          1.774762,
          1.535311,
          1.586829,
          1.559769,
          1.462834,
          1.638296,
          1.446253,
          1.235756,
          1.311619,
          1.392483,
          1.353855,
          1.298594,
          1.250238,
          1.186144,
          1.024902
        ],
        "null_C": [
          0.920486,
          1.053056,
          0.939914,
          0.922342,
          1.537833,
          1.3604,
          1.470549,
          1.443591,
          1.336168,
          1.774762,
          1.535311,
          1.586829,
          1.559769,
          1.462834,
          1.638296,
          1.446253,
          1.235756,
          1.311619,
          1.392483,
          1.353855,
          1.298594,
          1.250238,
          1.186144,
          1.024902
        ],
        "null_level_mean": 1.335083,
        "peak": {
          "peak_layer": 9,
          "peak_rel_depth": 0.3913,
          "peak_C": 1.774762
        },
        "peak_rel_depth_per_prompt": [
          0.3913,
          0.3913,
          0.3913,
          0.3913,
          0.3913,
          0.3913,
          0.3913,
          0.6087,
          0.6087,
          0.3913,
          0.3913,
          0.3913,
          0.3913,
          0.3913,
          0.3913,
          0.3913,
          0.3913,
          0.4348,
          0.1739,
          0.3913,
          0.3913,
          0.6087,
          0.3913,
          0.3913,
          0.1739,
          0.3913,
          0.2609,
          0.6957,
          0.4783,
          0.3913,
          0.3913,
          0.4783
        ],
        "peak_rel_depth_spread": 0.5218,
        "peak_over_null": 1.3293,
        "verdict": "smooth",
        "wall_s": 499.3
      }
    },
    "gpt2-medium": {
      "induction": {
        "model": "gpt2-medium",
        "hf_name": "gpt2-medium",
        "domain": "induction",
        "n_samples": 32,
        "n_layers": 24,
        "rel_depth": [
          0.0,
          0.0435,
          0.087,
          0.1304,
          0.1739,
          0.2174,
          0.2609,
          0.3043,
          0.3478,
          0.3913,
          0.4348,
          0.4783,
          0.5217,
          0.5652,
          0.6087,
          0.6522,
          0.6957,
          0.7391,
          0.7826,
          0.8261,
          0.8696,
          0.913,
          0.9565,
          1.0
        ],
        "entropy_H": [
          2.5371,
          2.2297,
          2.2087,
          1.8632,
          1.4665,
          1.2028,
          1.1449,
          1.3096,
          1.4886,
          1.2801,
          1.6178,
          1.4108,
          1.133,
          0.9644,
          1.0489,
          1.1563,
          0.9308,
          1.0511,
          1.1275,
          1.1929,
          1.2186,
          1.2476,
          1.6151,
          1.8177
        ],
        "specific_heat_C": [
          0.333946,
          0.808691,
          0.792365,
          1.018927,
          1.310177,
          1.356701,
          1.408536,
          1.305389,
          1.471779,
          1.397727,
          1.333621,
          1.455003,
          1.524536,
          1.529527,
          1.561514,
          1.642178,
          1.654562,
          1.605069,
          1.506153,
          1.611686,
          1.51,
          1.475312,
          1.385524,
          1.170695
        ],
        "null_C": [
          0.333946,
          0.808691,
          0.792365,
          1.018927,
          1.310177,
          1.356701,
          1.408536,
          1.305389,
          1.471779,
          1.397727,
          1.333621,
          1.455003,
          1.524536,
          1.529527,
          1.561514,
          1.642178,
          1.654562,
          1.605069,
          1.506153,
          1.611686,
          1.51,
          1.475312,
          1.385524,
          1.170695
        ],
        "null_level_mean": 1.340401,
        "peak": {
          "peak_layer": 16,
          "peak_rel_depth": 0.6957,
          "peak_C": 1.654562
        },
        "peak_rel_depth_per_prompt": [
          0.6522,
          0.9565,
          0.6522,
          0.8261,
          0.8261,
          0.6087,
          0.5652,
          0.6957,
          0.8261,
          0.6522,
          0.7391,
          0.6957,
          0.913,
          0.9565,
          0.6522,
          0.6957,
          0.7391,
          0.6522,
          0.6087,
          0.6522,
          0.8261,
          0.6522,
          0.6957,
          0.6522,
          0.8261,
          0.6522,
          0.8261,
          0.9565,
          0.4348,
          0.6957,
          0.6957,
          0.8261
        ],
        "peak_rel_depth_spread": 0.5217,
        "peak_over_null": 1.2344,
        "verdict": "smooth",
        "wall_s": 8.4
      },
      "relation_composition": {
        "model": "gpt2-medium",
        "hf_name": "gpt2-medium",
        "domain": "relation_composition",
        "n_samples": 32,
        "n_layers": 24,
        "rel_depth": [
          0.0,
          0.0435,
          0.087,
          0.1304,
          0.1739,
          0.2174,
          0.2609,
          0.3043,
          0.3478,
          0.3913,
          0.4348,
          0.4783,
          0.5217,
          0.5652,
          0.6087,
          0.6522,
          0.6957,
          0.7391,
          0.7826,
          0.8261,
          0.8696,
          0.913,
          0.9565,
          1.0
        ],
        "entropy_H": [
          2.6544,
          2.3477,
          2.29,
          1.9226,
          1.5266,
          1.2598,
          1.1865,
          1.3609,
          1.5661,
          1.2886,
          1.5933,
          1.4493,
          1.3646,
          1.0951,
          1.2554,
          1.3332,
          0.9801,
          1.1841,
          1.4122,
          1.4917,
          1.5954,
          1.5333,
          1.8607,
          2.0741
        ],
        "specific_heat_C": [
          0.347517,
          0.825803,
          0.865112,
          1.041266,
          1.358549,
          1.381077,
          1.466934,
          1.445545,
          1.565073,
          1.541317,
          1.494068,
          1.633081,
          1.640579,
          1.945909,
          1.769004,
          1.766905,
          1.743659,
          1.761892,
          1.6446,
          1.67395,
          1.545649,
          1.460886,
          1.356562,
          1.143656
        ],
        "null_C": [
          0.347517,
          0.825803,
          0.865112,
          1.041266,
          1.358549,
          1.381077,
          1.466934,
          1.445545,
          1.565073,
          1.541317,
          1.494068,
          1.633081,
          1.640579,
          1.945909,
          1.769004,
          1.766905,
          1.743659,
          1.761892,
          1.6446,
          1.67395,
          1.545649,
          1.460886,
          1.356562,
          1.143656
        ],
        "null_level_mean": 1.434108,
        "peak": {
          "peak_layer": 13,
          "peak_rel_depth": 0.5652,
          "peak_C": 1.945909
        },
        "peak_rel_depth_per_prompt": [
          0.8261,
          0.5652,
          0.5652,
          0.6087,
          0.5652,
          0.5652,
          0.7391,
          0.5652,
          0.5652,
          0.5652,
          0.5652,
          0.7391,
          0.6957,
          0.5652,
          0.5652,
          0.5217,
          0.6957,
          0.6957,
          0.6087,
          0.5652,
          0.5652,
          0.5652,
          0.8261,
          0.5652,
          0.5652,
          0.5652,
          0.5652,
          0.5652,
          0.5652,
          0.6957,
          0.5652,
          0.5652
        ],
        "peak_rel_depth_spread": 0.3044,
        "peak_over_null": 1.3569,
        "verdict": "smooth",
        "wall_s": 11.2
      }
    }
  },
  "verdict": "SMOOTH \u2014 C(L) peaks do not exceed shuffled-logit null by 2x."
}